proxbias/__init__.py
proxbias/arm_centering.py
proxbias/metrics.py
proxbias/scPerturb_processing_plotting.py
proxbias/cpg_processing/__init__.py
proxbias/cpg_processing/loading.py
proxbias/cpg_processing/transform.py
proxbias/data/AdamsonWeissman2016_GSM2406681_10X010_b5_w100_n150.csv
proxbias/data/FrangiehIzar2021_RNA_b5_w100_n150.csv
proxbias/data/PapalexiSatija2021_eccite_RNA_b5_w100_n150.csv
proxbias/data/README.md
proxbias/data/ReplogleWeissman2022_rpe1_b5_w100_n150.csv
proxbias/data/TianKampmann2021_CRISPRi_b5_w100_n150.csv
proxbias/data/cancerGeneList.tsv
proxbias/data/centromeres_hg38.tsv
proxbias/data/crispr.csv.gz
proxbias/data/hg38_cytoband.tsv.gz
proxbias/data/hg38_scaffolds.tsv
proxbias/data/ncbirefseq_hg38.tsv.gz
proxbias/data/plate.csv.gz
proxbias/data/shinyDepMap_19Q3_cluster_s.csv
proxbias/data/u2os.csv
proxbias/data/well.csv.gz
proxbias/depmap/__init__.py
proxbias/depmap/constants.py
proxbias/depmap/load.py
proxbias/depmap/process.py
proxbias/notebooks/DepMap_22q4_vs_23q2.ipynb
proxbias/notebooks/DepMap_PB_Driver_Analysis.ipynb
proxbias/notebooks/DepMap_PB_Driver_Scan_sample.ipynb
proxbias/notebooks/DepMap_PB_Drivers.ipynb
proxbias/notebooks/cpg0016_known_biology_metrics.ipynb
proxbias/notebooks/cpg0016_loading.ipynb
proxbias/notebooks/cpg0016_plots.ipynb
proxbias/notebooks/scPerturb_tables_heatmaps.ipynb
proxbias/notebooks/shinyDepMap_benchmark.ipynb
proxbias/plotting/__init__.py
proxbias/plotting/bm_bars.py
proxbias/plotting/centro_telo_scatter.py
proxbias/plotting/heatmaps.py
proxbias/utils/__init__.py
proxbias/utils/chromosome_info.py
proxbias/utils/constants.py
proxbias/utils/cosine_similarity.py
proxbias/utils/data_utils.py
proxbias/utils/df_tools.py
proxbias/utils/q_norm.py
proxbias-0.11.0.dist-info/METADATA
proxbias-0.11.0.dist-info/WHEEL
proxbias-0.11.0.dist-info/top_level.txt
proxbias-0.11.0.dist-info/RECORD
