Metadata-Version: 2.1
Name: proxbias
Version: 0.11.0
Author-email: Recursion Pharmaceuticals <devs@recursionpharma.com>
Keywords: proxbias
Classifier: Operating System :: OS Independent
Classifier: Programming Language :: Python
Classifier: Programming Language :: Python :: 3
Requires-Python: >=3.8
Requires-Dist: efaar-benchmarking >=0.1.0
Requires-Dist: fastparquet
Requires-Dist: importlib-resources
Requires-Dist: infercnvpy
Requires-Dist: numpy
Requires-Dist: pandas
Requires-Dist: pyarrow
Requires-Dist: s3fs
Requires-Dist: scanpy
Requires-Dist: scikit-image
Requires-Dist: scikit-learn
Requires-Dist: scipy
Requires-Dist: seaborn
Requires-Dist: statsmodels
Requires-Dist: tqdm
Requires-Dist: wget
Provides-Extra: dev
Requires-Dist: bandit ; extra == 'dev'
Requires-Dist: black[jupyter] ; extra == 'dev'
Requires-Dist: coverage ; extra == 'dev'
Requires-Dist: flake8 ; extra == 'dev'
Requires-Dist: isort ; extra == 'dev'
Requires-Dist: mypy ; extra == 'dev'
Requires-Dist: pip-tools ; extra == 'dev'
Requires-Dist: pre-commit ; extra == 'dev'
Requires-Dist: pytest ; extra == 'dev'
Requires-Dist: pytest-cov ; extra == 'dev'
Requires-Dist: pyupgrade ; extra == 'dev'
Requires-Dist: radon ; extra == 'dev'
Requires-Dist: types-pkg-resources ; extra == 'dev'
Requires-Dist: tox ; extra == 'dev'
Requires-Dist: validate-pyproject[all] ; extra == 'dev'
Requires-Dist: ipython <8.13.0 ; (python_version <= "3.8") and extra == 'dev'
Requires-Dist: ipython ; (python_version > "3.8") and extra == 'dev'
